ethology/__init__.py
ethology/datasets/__init__.py
ethology/datasets/split.py
ethology/io/__init__.py
ethology/io/annotations/__init__.py
ethology/io/annotations/load_bboxes.py
ethology/io/annotations/save_bboxes.py
ethology/validators/annotations.py
ethology/validators/detections.py
ethology/validators/utils.py
ethology/validators/json_schemas/__init__.py
ethology/validators/json_schemas/utils.py
ethology/validators/json_schemas/schemas/COCO_schema.json
ethology/validators/json_schemas/schemas/README.md
ethology/validators/json_schemas/schemas/VIA_schema.json
ethology-0.1.2.dist-info/licenses/LICENSE
ethology-0.1.2.dist-info/METADATA
ethology-0.1.2.dist-info/WHEEL
ethology-0.1.2.dist-info/top_level.txt
ethology-0.1.2.dist-info/RECORD
