Metadata-Version: 2.4
Name: ethology
Version: 0.1.2
Summary: Data processing tools for animal behavioural analysis
Author-email: Adam Tyson <code@adamltyson.com>
License: BSD-3-Clause
Project-URL: Homepage, https://github.com/neuroinformatics-unit/ethology
Project-URL: Bug Tracker, https://github.com/neuroinformatics-unit/ethology/issues
Project-URL: Documentation, https://github.com/neuroinformatics-unit/ethology
Project-URL: Source Code, https://github.com/neuroinformatics-unit/ethology
Project-URL: User Support, https://github.com/neuroinformatics-unit/ethology/issues
Classifier: Development Status :: 2 - Pre-Alpha
Classifier: Programming Language :: Python
Classifier: Programming Language :: Python :: 3
Classifier: Programming Language :: Python :: 3.11
Classifier: Programming Language :: Python :: 3.12
Classifier: Programming Language :: Python :: 3.13
Classifier: Operating System :: OS Independent
Classifier: License :: OSI Approved :: BSD License
Requires-Python: >=3.11.0
License-File: LICENSE
Requires-Dist: movement>=0.13.0
Requires-Dist: pandera[pandas]
Requires-Dist: pycocotools
Requires-Dist: scikit-learn
Requires-Dist: torch
Requires-Dist: torchvision
Requires-Dist: loguru
Requires-Dist: tables>=3.10.1
Provides-Extra: dev
Requires-Dist: pytest; extra == "dev"
Requires-Dist: pytest-cov; extra == "dev"
Requires-Dist: pytest-loguru; extra == "dev"
Requires-Dist: coverage; extra == "dev"
Requires-Dist: tox; extra == "dev"
Requires-Dist: mypy; extra == "dev"
Requires-Dist: pre-commit; extra == "dev"
Requires-Dist: ruff; extra == "dev"
Requires-Dist: codespell; extra == "dev"
Requires-Dist: setuptools_scm; extra == "dev"
Requires-Dist: pandas-stubs; extra == "dev"
Requires-Dist: types-attrs; extra == "dev"
Requires-Dist: check-manifest; extra == "dev"
Requires-Dist: types-PyYAML; extra == "dev"
Requires-Dist: types-requests; extra == "dev"
Dynamic: license-file
